mkdocs_quiz/__init__.py
mkdocs_quiz/plugin.py
tests/__init__.py
tests/base_test_case.py
tests/mock_quiz_data.py
tests/test_html_generation.py
tests/test_logic.py
tests/test_mock.py
tests/test_ui_components.py
mkdocs_quizz-0.0.2.dist-info/LICENSE
mkdocs_quizz-0.0.2.dist-info/METADATA
mkdocs_quizz-0.0.2.dist-info/WHEEL
mkdocs_quizz-0.0.2.dist-info/entry_points.txt
mkdocs_quizz-0.0.2.dist-info/top_level.txt
mkdocs_quizz-0.0.2.dist-info/RECORD
