Metadata-Version: 2.1
Name: mkdocs-quizz
Version: 0.0.2
Summary: A MkDocs plugin to create quiz
Home-page: UNKNOWN
Author-email: benjamin@proton.me
License: MIT
Project-URL: Bug Reports, https://github.com/bdllard/mkdocs_quiz/issues
Project-URL: Source, https://github.com/bdallard/mkdocs_quiz
Keywords: mkdocs plugin quiz
Platform: UNKNOWN
Requires-Dist: mkdocs >=1.0.4
Requires-Dist: beautifulsoup4 >=4.11.1
Requires-Dist: lxml >=4.9.1
Requires-Dist: pytest >=7.4.4
